{
	"country-code": "United States of América",
	"data": {
		"Canada": "San Francisco",
		"America": "Los Angeles",
		"Mexico": "San Diego",
		"Guatemala": "San Jose",
		"Belize": "Sacramento",
		"El Salvador": "Fresno",
		"Honduras": "Bakersfield",
		"Nicaragua": "Santa Barbara",
		"Costa Rica": "Redding",
		"Panama": "Crescent City",

		"Alaska": "Reno",
		"Cuba": "Las Vegas",
		"Puerto Rico": "Elko",
		"Hawaii": "Winnemucca",

		"Colombia": "Seattle",
		"Venezuela": "Tacoma",
		"Guiana": "Olympia",
		"Ecuador": "Everett",
		"Peru": "Bellingham",
		"Bolivia": "Portland",
		"Chile": "Spokane",
		"Paraguay": "Yakima",
		"Argentina": "Moses Lake",
		"Uruguay": "Richland",
		"Brazil": "Kennewick",

		"Greenland": ["Washington", "Las Vegas"],
		"Iceland": "Walla Walla",

		"Ireland": "Hermiston",
		"United Kingdom": "Pendleton",
		"Norway": "Pullman",
		"Sweden": "Lewiston",
		"Finland": "Grangeville",
		"Portugal": "Baker City",
		"Spain": "John Day",
		"France": "Redmond",
		"Belgium": "Prineville",
		"Netherlands": "Bend",
		"Germany": "Sunriver",
		"Switzerland": "Corvallis",
		"Austria": "Eugene",
		"Italy": "Salem",
		"Czechia": "Lincoln City",
		"Poland": "Newport",
		"Slovakia": "Florence",
		"Hungary": "Coos Bay",
		"Croatia": "Roseburg",
		"Bosnia": "Bandon",
		"Montenegro": "Grants Pass",
		"Albania": "Brookings",
		"Serbia": "Medford",
		"Kosovo": "Ashland",
		"North Macedônia": "Klamath Falls",
		"Romania": "Lakeview",
		"Ukraine": "Burns",
		"Moldova": "Ontario",
		"Belarus": "Caldwell",
		"Lithuania": "Nanpa",
		"Latvia": "Boise",
		"Estonia": "McDermitt",
		"Bulgaria": "Winnemucca",
		"Greece": "Mill City",

		"Turkiye": "Fernley",
		"Syria": "Reno",
		"Iraq": "Fallon",
		"Iran": "Tahoe",
		"Turkmenistan": "Yerington",
		"Uzbekistan": "Walker Lake",
		"Kazakhstan": "Luning",
		"Kyrgyzstan": "Mina",
		"Tajikistan": "Moscow",
		"Afghanistan": "Sandpoint",
		"Pakistan": "Missoula",
		"India": "Stevensville",
		"Nepal": "Hamilton",
		"Bhutan": "Salmon",
		"Myanmar": "Polson",
		"Thailand": "Kalispell",
		"Cambodia": "Whitefish",
		"Laos": "Deer Lodge",
		"Vietnam": "Anaconda",

		"Russia": "Helena",
		"China": "Butte",
		"Mongolia": "Dillon",
		"North Korea": "Idaho Falls",
		"South Korea": "Rexburg",
		"Japan": "Island Park",
		"Taiwan": "West Yellowstone",
		"Philippines": "Three Forks",
		"Indonesia": "Townsend",
		"Papua New Guinea": "Chateau",
		"Australia": "Columbia Falls",
		"New Zealand": "Shelby",

		"South Africa": "West Glacier",
		"Botswana": "Essex",
		"Namibia": "East Glacier",
		"Zimbabwe": "Browning",
		"Mozambique": "Babb",
		"Zambia": "Dupuyer",
		"Angola": "Choteau",
		"Tanzania": "Fairfield",
		"Democratic Republic of the Congo": "Augusta",
		"Republic of the Congo": "Cascade",
		"Gabon": "Great Falls",
		"Equatorial Guinea": "Belt",
		"Uganda": "Monarch",
		"Kenya": "Fort Benton",
		"Somalia": "Loma",
		"Cameroon": "Neihart",
		"Central African Republic": "Stanford",
		"South Sudan": "Windham",
		"Ethiopia": "Hobson",
		"Nigeria": "Moore",
		"Djibouti": "Judith Gap",
		"Eritrea": "Harlowton",
		"Sudan": "White Sulphur",
		"Chad": "Townsend",
		"Niger": "White Sulphur Springs",
		"Benin": "Wilsall",
		"Togo": "Bozeman",
		"Ghana": "Belgrade",
		"Côte d'Ivoire": "Three Forks",
		"Liberia": "Whitehall",
		"Sierra Leone": "Norris",
		"Guinea": "Ennis",
		"Guinea-Bissau": "West Yellowstone",
		"The Gambia": "Gardiner",
		"Senegal": "Pray",
		"Mauritania": "Livingston",
		"Mali": "Big Timber",
		"Algeria": "Greycliff",
		"Libya": "Reed Point",
		"Egypt": "Ryegate",
		"Israel": "Grass Range",
		"Jordan": "Lavina",

		"Saudi Arabia": "Taigen",
		"Yemen": "Winnett",
		"Oman": "Mosby",
		"United Arab Emirates": "Edwards",
		"Bahrain": "Jordan",
		"Qatar": "Roundup",
		"Kuwait": "Billings",
	}
}

